LICENSE
README.md
setup.cfg
setup.py
structured_log_json/__init__.py
structured_log_json/jsonformat.py
structured_log_json/jsonhandler.py
structured_log_json/jsonlogger.py
structured_log_json/jsonstr.py
structured_log_json/main.py
structured_log_json.egg-info/PKG-INFO
structured_log_json.egg-info/SOURCES.txt
structured_log_json.egg-info/dependency_links.txt
structured_log_json.egg-info/top_level.txt
structured_log_json.egg-info/zip-safe