Metadata-Version: 2.1
Name: structured-log-json
Version: 1.0.0.post2023
Summary: Python structured event expression in json log.
Home-page: https://gitee.com/putty_git/structured_event_expression_in_-json_python.git
Author: Qiao.putty&&yangdunstc
Author-email: yangdunstc@163.com
License: LICENSE
Platform: any
Classifier: Development Status :: 3 - Alpha
Classifier: Intended Audience :: Developers
Classifier: License :: OSI Approved :: MIT License
Classifier: Natural Language :: Chinese (Simplified)
Classifier: Operating System :: MacOS
Classifier: Operating System :: Microsoft
Classifier: Operating System :: POSIX
Classifier: Operating System :: Unix
Classifier: Topic :: System :: Logging
Classifier: Topic :: Software Development :: Libraries :: Python Modules
Classifier: Programming Language :: Python :: 3.10
Classifier: Programming Language :: Python :: 3.11
Classifier: Programming Language :: Python :: 3.12
Requires-Python: >=3.6.9
License-File: LICENSE
